[{"name":"Lovos","picture":[{"id":"att2hehO08EVZ2UTv","url":"https://dl.airtable.com/SODattM7SIeMSdqFXg2q_1.jpg","filename":"1.jpg","size":346777,"type":"image/jpeg","thumbnails":{"small":{"url":"https://dl.airtable.com/imcbaEURxyFWuUbJbAov_small_1.jpg","width":36,"height":36},"large":{"url":"https://dl.airtable.com/NMJ96VzvSaDiQC8GiGL5_large_1.jpg","width":512,"height":512}}}],"kodas":"lovos","produktai":["rec4rOGc679ozJ5e0","reccTE181tjAJ64KR"],"id":"rec6ubg1ba8XgjATD"},{"name":"Spintelės","picture":[{"id":"attHjoljROFgsMCsw","url":"https://dl.airtable.com/wC5c8SxmAy03emLA3QAR_Spintele%CC%87s_Cabinets.jpg","filename":"Spintelės_Cabinets.jpg","size":620475,"type":"image/jpeg","thumbnails":{"small":{"url":"https://dl.airtable.com/W7t4eaGFTQKHILlbgsPK_small_Spintele%CC%87s_Cabinets.jpg","width":36,"height":36},"large":{"url":"https://dl.airtable.com/BUqDu4OLS8miaa37YEjd_large_Spintele%CC%87s_Cabinets.jpg","width":512,"height":512}}}],"kodas":"spinteles","produktai":["rec1fES3AJ5tSgpDT","recPEaOz2d5x0ElXP","recnb7rehB7aKDobN","recCm2oMwPuhzr3Za","recRgTBHszcVqcSsb","recnPcbPkDn52tEzC","rec4B1TNWcayMkyAa","recrRGRj1P5XEpGzy","recC2hr2moQMeFjbt"],"id":"recUa9kdfyxQzpG2Y"},{"name":"Integruojami baldai","picture":[{"id":"attkT1Yeumku6CH3O","url":"https://dl.airtable.com/DhuCG3bGSouna6SNukRg_Integruojami%20baldai.jpg","filename":"Integruojami baldai.jpg","size":1123104,"type":"image/jpeg","thumbnails":{"small":{"url":"https://dl.airtable.com/mGudK42R6qVWyh9gLGcA_small_Integruojami%20baldai.jpg","width":36,"height":36},"large":{"url":"https://dl.airtable.com/8LA407zcT5zdJUe0XUaA_large_Integruojami%20baldai.jpg","width":512,"height":512}}}],"kodas":"int_baldai","produktai":["rec2BabPaRjbK5HMz","rec8Z3DGegtROa69X","recm2KC3oTl3aBgY8","recQ09sNooddOVBtX","recN67lv0dTjLtsIY","recw0IphUni40QFiU","rec7QGe9buQL71Sfa","recGEkGdNPAkCI9ZH","recMMoayJFDyKjtZw","reckIqo7Q2SJ8apyC","recw4ocaqrhdis5jn"],"id":"reciga60xO7iAjgzp"},{"name":"Stalai","picture":[{"id":"attx02dmlxzstjXP5","url":"https://dl.airtable.com/Jq2nrd2iTkeuvjl7Wn1s_Stalai_Tables.jpg","filename":"Stalai_Tables.jpg","size":392549,"type":"image/jpeg","thumbnails":{"small":{"url":"https://dl.airtable.com/ulJsewMFQsOHXuBPcR3q_small_Stalai_Tables.jpg","width":36,"height":36},"large":{"url":"https://dl.airtable.com/quSr1YaSSx61Gxqd6LMC_large_Stalai_Tables.jpg","width":512,"height":512}}}],"kodas":"stalai","produktai":["recsne6IbCYEa7Dpa","recEWhoOYTcvhGam4","recKvwlQULWkYSEXt","rec7bUc9m5aeHd5Sh","recVJnVkMGrFgrnXD","rec38MjWV3zsiEgKk","rec8HBp32ONa1NAIj","recM12oloVgy7XPyo","recgsgT9Vtrp4G3Fw","recn72h1JZpYAaJV6"],"id":"recxr8m55if6IzzXC"},{"name":"Kėdės","picture":[{"id":"att1htcCNzopmdKJx","url":"https://dl.airtable.com/1GkO3CR0TSGnE0fWy6VX_Ke%CC%87de%CC%87s_Chairs.jpg","filename":"Kėdės_Chairs.jpg","size":75897,"type":"image/jpeg","thumbnails":{"small":{"url":"https://dl.airtable.com/zOetwySTkWNVX7uYujGQ_small_Ke%CC%87de%CC%87s_Chairs.jpg","width":36,"height":36},"large":{"url":"https://dl.airtable.com/NNJRyw1PRq21b7lq1jtJ_large_Ke%CC%87de%CC%87s_Chairs.jpg","width":512,"height":512}}}],"kodas":"kedes","produktai":["recdc8qDDppLRgfBT","recRZ1vt3QXJN6AUG","rec7ULDzYXHCalW1j"],"id":"recycFNKRqNt0LWML"}]